{
  "version": "1.0.0",
  "contrats": [
    {
      "contrat": "Avizen",
      "fichier": "contrats/avizen.json",
      "profondeur": 0.743,
      "couverture_semantique": 0.385
    },
    {
      "contrat": "Avizen Pro",
      "fichier": "contrats/avizen_pro.json",
      "profondeur": 0.735,
      "couverture_semantique": 0.385
    },
    {
      "contrat": "Entour'Age",
      "fichier": "contrats/entour_age.json",
      "profondeur": 0.713,
      "couverture_semantique": 0.385
    },
    {
      "contrat": "Essen'Ciel (assurance obsèques)",
      "fichier": "contrats/essen_ciel_assurance_obseques.json",
      "profondeur": 0.745,
      "couverture_semantique": 0.385
    },
    {
      "contrat": "Essen'Ciel Patrimoine",
      "fichier": "contrats/essen_ciel_patrimoine.json",
      "profondeur": 0.675,
      "couverture_semantique": 0.231
    },
    {
      "contrat": "Excelium (assurance vie)",
      "fichier": "contrats/excelium_assurance_vie.json",
      "profondeur": 0.7,
      "couverture_semantique": 0.385
    },
    {
      "contrat": "Ma Protection Accident (Garantie des accidents de la vie)",
      "fichier": "contrats/ma_protection_accident_garantie_des_accidents_de_la_vie.json",
      "profondeur": 0.625,
      "couverture_semantique": 0.385
    },
    {
      "contrat": "Ma Retraite (plan d'épargne retraite individuel — PER)",
      "fichier": "contrats/ma_retraite_plan_d_epargne_retraite_individuel_per.json",
      "profondeur": 0.657,
      "couverture_semantique": 0.385
    },
    {
      "contrat": "Masterlife CREDIT",
      "fichier": "contrats/masterlife_credit.json",
      "profondeur": 0.75,
      "couverture_semantique": 0.385
    }
  ]
}